optilearn/__init__.py
optilearn/__version__.py
optilearn/files.py
optilearn/image.py
optilearn/nn.py
optilearn/optimal.py
optilearn/optimal_2.py
optilearn/sequential.py
optilearn/text.py
optilearn/word.py
optimal_data_selector/__init__.py
optimal_data_selector/__version__.py
optimal_data_selector/files.py
optimal_data_selector/image.py
optimal_data_selector/optimal.py
optimal_data_selector/optimal_2.py
optimal_data_selector/sequential.py
optimal_data_selector/text.py
optimal_data_selector/version.py
optimal_data_selector/word.py
optilearn-1.3.7.dist-info/LICENSE
optilearn-1.3.7.dist-info/METADATA
optilearn-1.3.7.dist-info/WHEEL
optilearn-1.3.7.dist-info/top_level.txt
optilearn-1.3.7.dist-info/RECORD
