Metadata-Version: 2.1
Name: optilearn
Version: 1.3.7
Summary: Use to train neural networks, A Package for optimize models, transfer or copy files from one directory to other, use for nlp short word treatment, choosing optimal data for ML models, use for Image Scraping , use in timeseries problem to split the data into train and test, Deal with emojis and emoticons in nlp, word tokenize, token, get the list of Punctuation marks and English Pronouns too, can be used to read text files
Home-page: https://github.com/about-optilearn
Author: Rohan Majumder
Author-email: majumderrohan2001@gmail.com
Keywords: Training Neural networks,Deeplearning,callbacks,neural network,converting text into tokens,transfer or copy files from one directory to other,get best data combination,read text files,text files,lock data combination,save data,English,Pronouns,Punctuations,English pronouns,Model training,optimise accuracy,lock data combination,gives best result,best data for ML models,works on text data also,short word treatment,Image Scraping,download images,Web Image Scraping,timeseries,splitting tim
Classifier: Development Status :: 1 - Planning
Classifier: Intended Audience :: Developers
Classifier: Programming Language :: Python :: 3
Classifier: Programming Language :: Python :: 3.1
Classifier: Programming Language :: Python :: 3.2
Classifier: Programming Language :: Python :: 3.3
Classifier: Programming Language :: Python :: 3.4
Classifier: Programming Language :: Python :: 3.5
Classifier: Programming Language :: Python :: 3.6
Classifier: Programming Language :: Python :: 3.7
Classifier: Programming Language :: Python :: 3.8
Classifier: Programming Language :: Python :: 3.10
Classifier: Programming Language :: Python :: 3.11
Classifier: Programming Language :: Python :: 3.9
Classifier: Programming Language :: Python :: 3.12
Classifier: Operating System :: Unix
Classifier: Operating System :: POSIX
Classifier: Operating System :: iOS
Classifier: Operating System :: MacOS :: MacOS X
Classifier: Operating System :: Microsoft :: Windows
License-File: LICENSE
Requires-Dist: pandas
Requires-Dist: numpy
Requires-Dist: h5py
Requires-Dist: scikit-learn
Requires-Dist: torch
